wordfeudbot/__init__.py
wordfeudbot/main.py
wordfeudbot/data/test.txt
wordfeudbot/data/wordlists/swedish.txt
wordfeudbot/wordfeud_logic/__init__.py
wordfeudbot/wordfeud_logic/board.py
wordfeudbot/wordfeud_logic/wordlist.py
wordfeudbot-1.1.0.dist-info/LICENSE.md
wordfeudbot-1.1.0.dist-info/METADATA
wordfeudbot-1.1.0.dist-info/WHEEL
wordfeudbot-1.1.0.dist-info/entry_points.txt
wordfeudbot-1.1.0.dist-info/top_level.txt
wordfeudbot-1.1.0.dist-info/RECORD
