Metadata-Version: 2.1
Name: wordfeudbot
Version: 1.1.0
Summary: A python script that automates the game of wordfeud
Home-page: https://github.com/Pricehacker/wordfeud-bot
Author: Pricehacker
Author-email: admin@system.gq
License: MIT
Platform: UNKNOWN
Classifier: Programming Language :: Python :: 3
Classifier: License :: OSI Approved :: MIT License
Classifier: Operating System :: OS Independent
Requires-Dist: coloredlogs
Requires-Dist: emoji
Requires-Dist: requests
Requires-Dist: urllib3
